AUTHORS
CHANGELOG.txt
DESCRIPTION
LICENSE
MANIFEST.in
README.rst
setup.cfg
setup.py
django_media_library.egg-info/PKG-INFO
django_media_library.egg-info/SOURCES.txt
django_media_library.egg-info/dependency_links.txt
django_media_library.egg-info/requires.txt
django_media_library.egg-info/top_level.txt
media_library/.coverage
media_library/__init__.py
media_library/admin.py
media_library/forms.py
media_library/models.py
media_library/urls.py
media_library/utils.py
media_library/views.py
media_library/migrations/0001_initial.py
media_library/migrations/__init__.py
media_library/static/media_library/css/styles.css
media_library/static/media_library/css/styles.less
media_library/static/media_library/js/preview.js
media_library/templates/media_library/mediaitem_delete.html
media_library/templates/media_library/mediaitem_image_form.html
media_library/templates/media_library/mediaitem_video_form.html
media_library/templates/media_library/medialibrary_edit.html
media_library/templates/media_library/medialibrary_upload.html
media_library/templates/media_library/partials/media_image.html
media_library/templates/media_library/partials/media_video.html
media_library/templates/media_library/partials/mediaitem_form.html
media_library/templates/media_library/partials/mediaitem_meta.html
media_library/templates/media_library/partials/video.html
media_library/tests/.coveragerc
media_library/tests/__init__.py
media_library/tests/factories.py
media_library/tests/forms_tests.py
media_library/tests/models_tests.py
media_library/tests/runtests.py
media_library/tests/south_settings.py
media_library/tests/test_settings.py
media_library/tests/urls.py
media_library/tests/utils_tests.py
media_library/tests/views_tests.py