Metadata-Version: 1.0
Name: django-media-library
Version: 0.3.6
Summary: A reusable Django app to let users organize their own media.
